{"defaultKeyStatistics":{"annualHoldingsTurnover":{},"enterpriseToRevenue":{"raw":18.686,"fmt":"18.69"},"beta3Year":{},"profitMargins":{"raw":0.02286,"fmt":"2.29%"},"enterpriseToEbitda":{"raw":137.907,"fmt":"137.91"},"52WeekChange":{"raw":5.160855,"fmt":"516.09%"},"morningStarRiskRating":{},"forwardEps":{"raw":5.52,"fmt":"5.52"},"revenueQuarterlyGrowth":{},"sharesOutstanding":{"raw":959854016,"fmt":"959.85M","longFmt":"959,854,016"},"fundInceptionDate":{},"annualReportExpenseRatio":{},"totalAssets":{},"bookValue":{"raw":23.151,"fmt":"23.15"},"sharesShort":{"raw":44732793,"fmt":"44.73M","longFmt":"44,732,793"},"sharesPercentSharesOut":{"raw":0.0466,"fmt":"4.66%"},"fundFamily":null,"lastFiscalYearEnd":{"raw":1609372800,"fmt":"2020-12-31"},"heldPercentInstitutions":{"raw":0.42529,"fmt":"42.53%"},"netIncomeToCommon":{"raw":690000000,"fmt":"690M","longFmt":"690,000,000"},"trailingEps":{"raw":0.64,"fmt":"0.64"},"lastDividendValue":{},"SandP52WeekChange":{"raw":0.5131594,"fmt":"51.32%"},"priceToBook":{"raw":26.724981,"fmt":"26.72"},"heldPercentInsiders":{"raw":0.19985001,"fmt":"19.99%"},"nextFiscalYearEnd":{"raw":1672444800,"fmt":"2022-12-31"},"yield":{},"mostRecentQuarter":{"raw":1609372800,"fmt":"2020-12-31"},"shortRatio":{"raw":1.09,"fmt":"1.09"},"sharesShortPreviousMonthDate":{"raw":1613088000,"fmt":"2021-02-12"},"floatShares":{"raw":771319079,"fmt":"771.32M","longFmt":"771,319,079"},"beta":{"raw":2.06013,"fmt":"2.06"},"enterpriseValue":{"raw":589277954048,"fmt":"589.28B","longFmt":"589,277,954,048"},"priceHint":{"raw":2,"fmt":"2","longFmt":"2"},"threeYearAverageReturn":{},"lastSplitDate":{"raw":1598832000,"fmt":"2020-08-31"},"lastSplitFactor":"5:1","legalType":null,"lastDividendDate":{},"morningStarOverallRating":{},"earningsQuarterlyGrowth":{"raw":1.571,"fmt":"157.10%"},"priceToSalesTrailing12Months":{},"dateShortInterest":{"raw":1615766400,"fmt":"2021-03-15"},"pegRatio":{"raw":4.95,"fmt":"4.95"},"ytdReturn":{},"forwardPE":{"raw":112.08515,"fmt":"112.09"},"maxAge":1,"lastCapGain":{},"shortPercentOfFloat":{"raw":0.058000002,"fmt":"5.80%"},"sharesShortPriorMonth":{"raw":47692184,"fmt":"47.69M","longFmt":"47,692,184"},"impliedSharesOutstanding":{},"category":null,"fiveYearAverageReturn":{}},"financialsTemplate":{"code":"N","maxAge":1},"price":{"quoteSourceName":"Nasdaq Real Time Price","regularMarketOpen":{"raw":641.87,"fmt":"641.87"},"averageDailyVolume3Month":{"raw":35807911,"fmt":"35.81M","longFmt":"35,807,911"},"exchange":"NMS","regularMarketTime":1616788802,"volume24Hr":{},"regularMarketDayHigh":{"raw":643.82,"fmt":"643.82"},"shortName":"Tesla, Inc.","averageDailyVolume10Day":{"raw":36605000,"fmt":"36.6M","longFmt":"36,605,000"},"longName":"Tesla, Inc.","regularMarketChange":{"raw":-21.679993,"fmt":"-21.68"},"currencySymbol":"$","regularMarketPreviousClose":{"raw":640.39,"fmt":"640.39"},"postMarketTime":1616803197,"preMarketPrice":{"raw":606,"fmt":"606.00"},"preMarketTime":1617006896,"exchangeDataDelayedBy":0,"toCurrency":null,"postMarketChange":{"raw":2.789978,"fmt":"2.79"},"postMarketPrice":{"raw":621.5,"fmt":"621.50"},"exchangeName":"NasdaqGS","preMarketChange":{"raw":-12.710022,"fmt":"-12.71"},"circulatingSupply":{},"regularMarketDayLow":{"raw":599.9,"fmt":"599.90"},"priceHint":{"raw":2,"fmt":"2","longFmt":"2"},"currency":"USD","regularMarketPrice":{"raw":618.71,"fmt":"618.71"},"regularMarketVolume":{"raw":33852833,"fmt":"33.85M","longFmt":"33,852,833.00"},"lastMarket":null,"regularMarketSource":"FREE_REALTIME","openInterest":{},"marketState":"PRE","underlyingSymbol":null,"marketCap":{"raw":593871306752,"fmt":"593.87B","longFmt":"593,871,306,752.00"},"quoteType":"EQUITY","preMarketChangePercent":{"raw":-0.020542776,"fmt":"-2.05%"},"volumeAllCurrencies":{},"postMarketSource":"DELAYED","strikePrice":{},"symbol":"TSLA","postMarketChangePercent":{"raw":0.0045093466,"fmt":"0.45%"},"preMarketSource":"FREE_REALTIME","maxAge":1,"fromCurrency":null,"regularMarketChangePercent":{"raw":-0.033854358,"fmt":"-3.39%"}},"financialData":{"ebitdaMargins":{"raw":0.1355,"fmt":"13.55%"},"profitMargins":{"raw":0.02286,"fmt":"2.29%"},"grossMargins":{"raw":0.21023001,"fmt":"21.02%"},"operatingCashflow":{"raw":5943000064,"fmt":"5.94B","longFmt":"5,943,000,064"},"revenueGrowth":{"raw":0.455,"fmt":"45.50%"},"operatingMargins":{"raw":0.061869998,"fmt":"6.19%"},"ebitda":{"raw":4272999936,"fmt":"4.27B","longFmt":"4,272,999,936"},"targetLowPrice":{"raw":67,"fmt":"67.00"},"recommendationKey":"hold","grossProfits":{"raw":6630000000,"fmt":"6.63B","longFmt":"6,630,000,000"},"freeCashflow":{"raw":3401374976,"fmt":"3.4B","longFmt":"3,401,374,976"},"targetMedianPrice":{"raw":727.5,"fmt":"727.50"},"currentPrice":{"raw":618.71,"fmt":"618.71"},"earningsGrowth":{"raw":1.055,"fmt":"105.50%"},"currentRatio":{"raw":1.875,"fmt":"1.88"},"returnOnAssets":{"raw":0.028210001,"fmt":"2.82%"},"numberOfAnalystOpinions":{"raw":30,"fmt":"30","longFmt":"30"},"targetMeanPrice":{"raw":621.5,"fmt":"621.50"},"debtToEquity":{"raw":56.324,"fmt":"56.32"},"returnOnEquity":{"raw":0.054229997,"fmt":"5.42%"},"targetHighPrice":{"raw":1200,"fmt":"1,200.00"},"totalCash":{"raw":19384000512,"fmt":"19.38B","longFmt":"19,384,000,512"},"totalDebt":{"raw":13336999936,"fmt":"13.34B","longFmt":"13,336,999,936"},"totalRevenue":{"raw":31536001024,"fmt":"31.54B","longFmt":"31,536,001,024"},"totalCashPerShare":{"raw":20.195,"fmt":"20.19"},"financialCurrency":"USD","maxAge":86400,"revenuePerShare":{"raw":33.801,"fmt":"33.80"},"quickRatio":{"raw":1.494,"fmt":"1.49"},"recommendationMean":{"raw":2.9,"fmt":"2.90"}},"quoteType":{"exchange":"NMS","shortName":"Tesla, Inc.","longName":"Tesla, Inc.","exchangeTimezoneName":"America/New_York","exchangeTimezoneShortName":"EDT","isEsgPopulated":false,"gmtOffSetMilliseconds":"-14400000","quoteType":"EQUITY","symbol":"TSLA","messageBoardId":"finmb_27444752","market":"us_market"},"calendarEvents":{"maxAge":1,"earnings":{"earningsDate":[{"raw":1619481600,"fmt":"2021-04-27"},{"raw":1620000000,"fmt":"2021-05-03"}],"earningsAverage":{"raw":0.74,"fmt":"0.74"},"earningsLow":{"raw":0.46,"fmt":"0.46"},"earningsHigh":{"raw":0.97,"fmt":"0.97"},"revenueAverage":{"raw":9916330000,"fmt":"9.92B","longFmt":"9,916,330,000"},"revenueLow":{"raw":8368000000,"fmt":"8.37B","longFmt":"8,368,000,000"},"revenueHigh":{"raw":12341300000,"fmt":"12.34B","longFmt":"12,341,300,000"}},"exDividendDate":{},"dividendDate":{}},"summaryDetail":{"previousClose":{"raw":640.39,"fmt":"640.39"},"regularMarketOpen":{"raw":641.87,"fmt":"641.87"},"twoHundredDayAverage":{"raw":606.0842,"fmt":"606.08"},"trailingAnnualDividendYield":{},"payoutRatio":{"raw":0,"fmt":"0.00%"},"volume24Hr":{},"regularMarketDayHigh":{"raw":643.82,"fmt":"643.82"},"navPrice":{},"averageDailyVolume10Day":{"raw":36605000,"fmt":"36.6M","longFmt":"36,605,000"},"totalAssets":{},"regularMarketPreviousClose":{"raw":640.39,"fmt":"640.39"},"fiftyDayAverage":{"raw":706.2715,"fmt":"706.27"},"trailingAnnualDividendRate":{},"open":{"raw":641.87,"fmt":"641.87"},"toCurrency":null,"averageVolume10days":{"raw":36605000,"fmt":"36.6M","longFmt":"36,605,000"},"expireDate":{},"yield":{},"algorithm":null,"dividendRate":{},"exDividendDate":{},"beta":{"raw":2.06013,"fmt":"2.06"},"circulatingSupply":{},"startDate":{},"regularMarketDayLow":{"raw":599.9,"fmt":"599.90"},"priceHint":{"raw":2,"fmt":"2","longFmt":"2"},"currency":"USD","trailingPE":{"raw":966.73444,"fmt":"966.73"},"regularMarketVolume":{"raw":33852833,"fmt":"33.85M","longFmt":"33,852,833"},"lastMarket":null,"maxSupply":{},"openInterest":{},"marketCap":{"raw":593871306752,"fmt":"593.87B","longFmt":"593,871,306,752"},"volumeAllCurrencies":{},"strikePrice":{},"averageVolume":{"raw":35807911,"fmt":"35.81M","longFmt":"35,807,911"},"priceToSalesTrailing12Months":{"raw":18.831535,"fmt":"18.83"},"dayLow":{"raw":599.9,"fmt":"599.90"},"ask":{"raw":0,"fmt":"0.00"},"ytdReturn":{},"askSize":{"raw":900,"fmt":"900","longFmt":"900"},"volume":{"raw":33852833,"fmt":"33.85M","longFmt":"33,852,833"},"fiftyTwoWeekHigh":{"raw":900.4,"fmt":"900.40"},"forwardPE":{"raw":112.08515,"fmt":"112.09"},"maxAge":1,"fromCurrency":null,"fiveYearAvgDividendYield":{},"fiftyTwoWeekLow":{"raw":89.28,"fmt":"89.28"},"bid":{"raw":0,"fmt":"0.00"},"tradeable":false,"dividendYield":{},"bidSize":{"raw":3000,"fmt":"3k","longFmt":"3,000"},"dayHigh":{"raw":643.82,"fmt":"643.82"}},"symbol":"TSLA","pageViews":{"shortTermTrend":"DOWN","midTermTrend":"UP","longTermTrend":"UP","maxAge":1},"quoteData":{"TSLA":{"sourceInterval":15,"quoteSourceName":"Delayed Quote","regularMarketOpen":{"raw":641.87,"fmt":"641.87"},"exchange":"NMS","regularMarketTime":{"raw":1616788802,"fmt":"4:00PM EDT"},"fiftyTwoWeekRange":{"raw":"89.28 - 900.4","fmt":"89.28 - 900.40"},"sharesOutstanding":{"raw":959854016,"fmt":"959.854M","longFmt":"959,854,016"},"regularMarketDayHigh":{"raw":643.82,"fmt":"643.82"},"shortName":"Tesla, Inc.","longName":"Tesla, Inc.","exchangeTimezoneName":"America/New_York","regularMarketChange":{"raw":-21.679993,"fmt":"-21.68"},"regularMarketPreviousClose":{"raw":640.39,"fmt":"640.39"},"fiftyTwoWeekHighChange":{"raw":-281.69,"fmt":"-281.69"},"exchangeTimezoneShortName":"EDT","fiftyTwoWeekLowChange":{"raw":529.43005,"fmt":"529.43"},"exchangeDataDelayedBy":0,"regularMarketDayLow":{"raw":599.9,"fmt":"599.90"},"priceHint":2,"currency":"USD","regularMarketPrice":{"raw":618.71,"fmt":"618.71"},"regularMarketVolume":{"raw":33852833,"fmt":"33.853M","longFmt":"33,852,833"},"isLoading":false,"triggerable":true,"gmtOffSetMilliseconds":-14400000,"firstTradeDateMilliseconds":1277818200000,"region":"US","marketState":"PRE","marketCap":{"raw":593871306752,"fmt":"593.871B","longFmt":"593,871,306,752"},"quoteType":"EQUITY","invalid":false,"symbol":"TSLA","language":"en-US","fiftyTwoWeekLowChangePercent":{"raw":5.929996,"fmt":"593.00%"},"regularMarketDayRange":{"raw":"599.9 - 643.82","fmt":"599.90 - 643.82"},"messageBoardId":"finmb_27444752","fiftyTwoWeekHigh":{"raw":900.4,"fmt":"900.40"},"fiftyTwoWeekHighChangePercent":{"raw":-0.31284985,"fmt":"-31.28%"},"uuid":"ec367bc4-f92c-397c-ac81-bf7b43cffaf7","market":"us_market","fiftyTwoWeekLow":{"raw":89.28,"fmt":"89.28"},"regularMarketChangePercent":{"raw":-3.3854358,"fmt":"-3.39%"},"fullExchangeName":"NasdaqGS","tradeable":false}},"mktmData":{}}